{
  "VCALENDAR": [
    {
      "PRODID": "-//Google Inc//Google Calendar 70.9054//EN",
      "VERSION": "2.0",
      "CALSCALE": "GREGORIAN",
      "METHOD": "PUBLISH",
      "X-WR-CALNAME": "kamalkc@bnks.edu.np",
      "X-WR-TIMEZONE": "Asia/Kolkata",
      "VEVENT": [
      
        {
          "DTSTART": "20250102T083000Z",
          "DTEND": "20250102T093000Z",
          "DTSTAMP": "20250215T075322Z",
          "UID": "5sl62ee6465k9oooqio3lhnkcu@google.com",
          "CREATED": "20240920T050212Z",
          "LAST-MODIFIED": "20240920T050212Z",
          "SEQUENCE": "0",
          "STATUS": "CONFIRMED",
          "SUMMARY": "Sports Day Rehearsal",
          "TRANSP": "OPAQUE"
        },
        {
          "DTSTART;VALUE=DATE": "20250104",
          "DTEND;VALUE=DATE": "20250105",
          "DTSTAMP": "20250215T075322Z",
          "UID": "2hd8hpovgm29f8ij4ft5jn1j4p@google.com",
          "CREATED": "20240920T050223Z",
          "LAST-MODIFIED": "20240920T050223Z",
          "SEQUENCE": "0",
          "STATUS": "CONFIRMED",
          "SUMMARY": "Sports Day ",
          "TRANSP": "TRANSPARENT"
        },
        {
          "DTSTART;VALUE=DATE": "20250104",
          "DTEND;VALUE=DATE": "20250105",
          "DTSTAMP": "20250215T075322Z",
          "UID": "224amcm927hs026nnkpfk17l73@google.com",
          "CREATED": "20240920T050250Z",
          "LAST-MODIFIED": "20240920T050250Z",
          "SEQUENCE": "0",
          "STATUS": "CONFIRMED",
          "SUMMARY": "Students go home with Report Card After Program",
          "TRANSP": "TRANSPARENT"
        },
        {
          "DTSTART;VALUE=DATE": "20250104",
          "DTEND;VALUE=DATE": "20250105",
          "DTSTAMP": "20250215T075322Z",
          "UID": "35m65v4sohikqkvbu3vcfie7mj@google.com",
          "CREATED": "20240920T050354Z",
          "LAST-MODIFIED": "20240920T050354Z",
          "SEQUENCE": "0",
          "STATUS": "CONFIRMED",
          "SUMMARY": "Winter break begins ",
          "TRANSP": "TRANSPARENT"
        },
        {
          "DTSTART;VALUE=DATE": "20250106",
          "DTEND;VALUE=DATE": "20250107",
          "DTSTAMP": "20250215T075322Z",
          "UID": "0iejcf11guqqsinphpa0riuf2r@google.com",
          "CREATED": "20240920T050437Z",
          "LAST-MODIFIED": "20240920T050437Z",
          "SEQUENCE": "0",
          "STATUS": "CONFIRMED",
          "SUMMARY": "Workshop for Teachers",
          "TRANSP": "TRANSPARENT"
        },
        {
          "DTSTART;VALUE=DATE": "20250107",
          "DTEND;VALUE=DATE": "20250108",
          "DTSTAMP": "20250215T075322Z",
          "UID": "45gh8anv1q5kfgcee2csbbij0l@google.com",
          "CREATED": "20240920T050458Z",
          "LAST-MODIFIED": "20240920T050458Z",
          "SEQUENCE": "0",
          "STATUS": "CONFIRMED",
          "SUMMARY": "Workshop for Teachers",
          "TRANSP": "TRANSPARENT"
        },
        {
          "DTSTART;VALUE=DATE": "20250108",
          "DTEND;VALUE=DATE": "20250109",
          "DTSTAMP": "20250215T075322Z",
          "UID": "0e4r7r484kqq19dln9au05k53f@google.com",
          "CREATED": "20240920T050522Z",
          "LAST-MODIFIED": "20240920T050522Z",
          "SEQUENCE": "0",
          "STATUS": "CONFIRMED",
          "SUMMARY": "Workshop for Teachers",
          "TRANSP": "TRANSPARENT"
        },
        {
          "DTSTART;VALUE=DATE": "20250111",
          "DTEND;VALUE=DATE": "20250112",
          "DTSTAMP": "20250215T075322Z",
          "UID": "0g47n1tjb7hjcfljuhkv6oohse@google.com",
          "CREATED": "20240920T050638Z",
          "LAST-MODIFIED": "20240920T050638Z",
          "SEQUENCE": "0",
          "STATUS": "CONFIRMED",
          "SUMMARY": "National Math League (Math Club) in Collaboration with Culinary Club Prithi Jayanti ",
          "TRANSP": "TRANSPARENT"
        },
        {
          "DTSTART;VALUE=DATE": "20250112",
          "DTEND;VALUE=DATE": "20250113",
          "DTSTAMP": "20250215T075322Z",
          "UID": "6l1rflc8q1vpb3ra7qk9bm51ji@google.com",
          "CREATED": "20240920T050706Z",
          "LAST-MODIFIED": "20240920T050706Z",
          "SEQUENCE": "0",
          "STATUS": "CONFIRMED",
          "SUMMARY": "National Math League (Math Club)",
          "TRANSP": "TRANSPARENT"
        },
        {
          "DTSTART;VALUE=DATE": "20250112",
          "DTEND;VALUE=DATE": "20250113",
          "DTSTAMP": "20250215T075322Z",
          "UID": "6uebn92gufl1ndk6mecobenac6@google.com",
          "CREATED": "20240920T050730Z",
          "LAST-MODIFIED": "20240920T050730Z",
          "SEQUENCE": "0",
          "STATUS": "CONFIRMED",
          "SUMMARY": "Inter School Art Workshop Starts (Art Club)",
          "TRANSP": "TRANSPARENT"
        },
        {
          "DTSTART;VALUE=DATE": "20250114",
          "DTEND;VALUE=DATE": "20250115",
          "DTSTAMP": "20250215T075322Z",
          "UID": "7ue25l84460bb130ltadcni5g3@google.com",
          "CREATED": "20240920T050739Z",
          "LAST-MODIFIED": "20240920T050739Z",
          "SEQUENCE": "0",
          "STATUS": "CONFIRMED",
          "SUMMARY": "Maghi Parva ",
          "TRANSP": "TRANSPARENT"
        },
        {
          "DTSTART;VALUE=DATE": "20250114",
          "DTEND;VALUE=DATE": "20250115",
          "DTSTAMP": "20250215T075322Z",
          "UID": "3rhl02ui1e5smle4kncdog1s2j@google.com",
          "CREATED": "20240920T050800Z",
          "LAST-MODIFIED": "20240920T050800Z",
          "SEQUENCE": "0",
          "STATUS": "CONFIRMED",
          "SUMMARY": "Inter School MUN Begins (Interact Club)",
          "TRANSP": "TRANSPARENT"
        },
        {
          "DTSTART;VALUE=DATE": "20250117",
          "DTEND;VALUE=DATE": "20250118",
          "DTSTAMP": "20250215T075322Z",
          "UID": "6tokjl7jkdl36747df9d9l8bsv@google.com",
          "CREATED": "20240920T050816Z",
          "LAST-MODIFIED": "20240920T050816Z",
          "SEQUENCE": "0",
          "STATUS": "CONFIRMED",
          "SUMMARY": "Inter School MUN Ends",
          "TRANSP": "TRANSPARENT"
        },
        {
          "DTSTART": "20250118T113000Z",
          "DTEND": "20250118T123000Z",
          "DTSTAMP": "20250215T075322Z",
          "UID": "07a3dn74qjc007vfgvbeop0oc7@google.com",
          "CREATED": "20240920T050840Z",
          "LAST-MODIFIED": "20240920T050840Z",
          "SEQUENCE": "0",
          "STATUS": "CONFIRMED",
          "SUMMARY": "Students must return by",
          "TRANSP": "OPAQUE"
        },
        {
          "DTSTART;VALUE=DATE": "20250119",
          "DTEND;VALUE=DATE": "20250120",
          "DTSTAMP": "20250215T075322Z",
          "UID": "1h3v135qv3phopcqhhppjgapci@google.com",
          "CREATED": "20240920T050904Z",
          "LAST-MODIFIED": "20240920T050904Z",
          "SEQUENCE": "0",
          "STATUS": "CONFIRMED",
          "SUMMARY": "Clothing Drive Begins (Social Service Club)",
          "TRANSP": "TRANSPARENT"
        },
        {
          "DTSTART;VALUE=DATE": "20250120",
          "DTEND;VALUE=DATE": "20250121",
          "DTSTAMP": "20250215T075322Z",
          "UID": "67kc3dm6nkd29tecd51hvgjs62@google.com",
          "CREATED": "20240920T050918Z",
          "LAST-MODIFIED": "20240920T050918Z",
          "SEQUENCE": "0",
          "STATUS": "CONFIRMED",
          "SUMMARY": "Class 10 Final Examination Begins",
          "TRANSP": "TRANSPARENT"
        },
        {
          "DTSTART;VALUE=DATE": "20250121",
          "DTEND;VALUE=DATE": "20250122",
          "DTSTAMP": "20250215T075322Z",
          "UID": "55dc7ctscg9ac9kpjjdrqc626h@google.com",
          "CREATED": "20240920T050927Z",
          "LAST-MODIFIED": "20240920T050927Z",
          "SEQUENCE": "0",
          "STATUS": "CONFIRMED",
          "SUMMARY": "Clothing Drive Ends",
          "TRANSP": "TRANSPARENT"
        },
        {
          "DTSTART": "20250123T104500Z",
          "DTEND": "20250123T114500Z",
          "DTSTAMP": "20250215T075322Z",
          "UID": "4j66ckb2ft99b17f286mk5vp35@google.com",
          "CREATED": "20240920T050952Z",
          "LAST-MODIFIED": "20240920T051011Z",
          "SEQUENCE": "0",
          "STATUS": "CONFIRMED",
          "SUMMARY": "Python Programming Competiton for Grades 8-9",
          "TRANSP": "OPAQUE"
        },
        {
          "DTSTART;VALUE=DATE": "20250124",
          "DTEND;VALUE=DATE": "20250125",
          "DTSTAMP": "20250215T075322Z",
          "UID": "23rq1akgrqd37kpn8grvpcnbfb@google.com",
          "CREATED": "20240920T051036Z",
          "LAST-MODIFIED": "20240920T051036Z",
          "SEQUENCE": "0",
          "STATUS": "CONFIRMED",
          "SUMMARY": "Movie Night for BL in Respective House (Theatre Club)",
          "TRANSP": "TRANSPARENT"
        },
        {
          "DTSTART;VALUE=DATE": "20250125",
          "DTEND;VALUE=DATE": "20250126",
          "DTSTAMP": "20250215T075322Z",
          "UID": "4r505llheek40sh6u6194ruoql@google.com",
          "CREATED": "20240920T051058Z",
          "LAST-MODIFIED": "20240920T051058Z",
          "SEQUENCE": "0",
          "STATUS": "CONFIRMED",
          "SUMMARY": "Nilgiri House and Pumori House Picnic",
          "TRANSP": "TRANSPARENT"
        },
        {
          "DTSTART;VALUE=DATE": "20250125",
          "DTEND;VALUE=DATE": "20250126",
          "DTSTAMP": "20250215T075322Z",
          "UID": "75kqe0hh372kg267vinok27jdc@google.com",
          "CREATED": "20240920T051117Z",
          "LAST-MODIFIED": "20240920T051117Z",
          "SEQUENCE": "0",
          "STATUS": "CONFIRMED",
          "SUMMARY": "Hiunchuli and Saipal House Day Trek ",
          "TRANSP": "TRANSPARENT"
        },
        {
          "DTSTART;VALUE=DATE": "20250125",
          "DTEND;VALUE=DATE": "20250126",
          "DTSTAMP": "20250215T075322Z",
          "UID": "73opidagbq7jdi8j14int3ndd1@google.com",
          "CREATED": "20240920T051133Z",
          "LAST-MODIFIED": "20240920T051133Z",
          "SEQUENCE": "0",
          "STATUS": "CONFIRMED",
          "SUMMARY": "Youth Meet Begins (SFON Club)",
          "TRANSP": "TRANSPARENT"
        },
        {
          "DTSTART;VALUE=DATE": "20250127",
          "DTEND;VALUE=DATE": "20250128",
          "DTSTAMP": "20250215T075322Z",
          "UID": "3f5b07ejhgtapsj09f1jke4v4c@google.com",
          "CREATED": "20240920T051145Z",
          "LAST-MODIFIED": "20240920T051145Z",
          "SEQUENCE": "0",
          "STATUS": "CONFIRMED",
          "SUMMARY": "Class 10 Final Examination Ends ",
          "TRANSP": "TRANSPARENT"
        },
        {
          "DTSTART;VALUE=DATE": "20250129",
          "DTEND;VALUE=DATE": "20250130",
          "DTSTAMP": "20250215T075322Z",
          "UID": "5h1jk3kpm3np54nouohs5e07b0@google.com",
          "CREATED": "20240920T051202Z",
          "LAST-MODIFIED": "20240920T051202Z",
          "SEQUENCE": "0",
          "STATUS": "CONFIRMED",
          "SUMMARY": "Sahid Diwas - a holiday",
          "TRANSP": "TRANSPARENT"
        },
        {
          "DTSTART;VALUE=DATE": "20250129",
          "DTEND;VALUE=DATE": "20250130",
          "DTSTAMP": "20250215T075322Z",
          "UID": "6sfeq12p7d2k9kv4d0cvh2kldj@google.com",
          "CREATED": "20240920T051217Z",
          "LAST-MODIFIED": "20240920T051217Z",
          "SEQUENCE": "0",
          "STATUS": "CONFIRMED",
          "SUMMARY": "Youth Meet Ends ",
          "TRANSP": "TRANSPARENT"
        },
        {
          "DTSTART;VALUE=DATE": "20250129",
          "DTEND;VALUE=DATE": "20250130",
          "DTSTAMP": "20250215T075322Z",
          "UID": "2031goim4a6m9toepviju8ncdp@google.com",
          "CREATED": "20240920T051232Z",
          "LAST-MODIFIED": "20240920T051232Z",
          "SEQUENCE": "0",
          "STATUS": "CONFIRMED",
          "SUMMARY": "Photo Walk (Photography Club)",
          "TRANSP": "TRANSPARENT"
        },
        {
          "DTSTART;VALUE=DATE": "20250130",
          "DTEND;VALUE=DATE": "20250131",
          "DTSTAMP": "20250215T075322Z",
          "UID": "3t9a26phasjbh99kvuans5h3oa@google.com",
          "CREATED": "20240920T051242Z",
          "LAST-MODIFIED": "20240920T051242Z",
          "SEQUENCE": "0",
          "STATUS": "CONFIRMED",
          "SUMMARY": "Sonam Lhosar",
          "TRANSP": "TRANSPARENT"
        },
        {
          "DTSTART;VALUE=DATE": "20250131",
          "DTEND;VALUE=DATE": "20250201",
          "DTSTAMP": "20250215T075322Z",
          "UID": "6fql78p1m1qisv5081jndbarcr@google.com",
          "CREATED": "20240920T051343Z",
          "LAST-MODIFIED": "20240920T051343Z",
          "SEQUENCE": "0",
          "STATUS": "CONFIRMED",
          "SUMMARY": "Ends of Fourth / Fifth Grade Assessment for Classes 8-12 A1\\, A2\\, / 5-7 ",
          "TRANSP": "TRANSPARENT"
        },
        {
          "DTSTART": "20250131T110000Z",
          "DTEND": "20250131T120000Z",
          "DTSTAMP": "20250215T075322Z",
          "UID": "2u6ua54s1k75ubdi6nekamhood@google.com",
          "CREATED": "20240920T051401Z",
          "LAST-MODIFIED": "20240920T051401Z",
          "SEQUENCE": "0",
          "STATUS": "CONFIRMED",
          "SUMMARY": "Almuni Talk Show",
          "TRANSP": "OPAQUE"
        },
        {
          "DTSTART": "20250131T140000Z",
          "DTEND": "20250131T150000Z",
          "DTSTAMP": "20250215T075322Z",
          "UID": "2n6auq0injivqt5qq2gn3bal8c@google.com",
          "CREATED": "20240920T051424Z",
          "LAST-MODIFIED": "20240920T051424Z",
          "SEQUENCE": "0",
          "STATUS": "CONFIRMED",
          "SUMMARY": "H/H Cultural Night",
          "TRANSP": "OPAQUE"
        },
        {
          "DTSTART;VALUE=DATE": "20250201",
          "DTEND;VALUE=DATE": "20250202",
          "DTSTAMP": "20250215T075322Z",
          "UID": "5kn5q7tbviugl67n2e9ocvj3hh@google.com",
          "CREATED": "20240920T051459Z",
          "LAST-MODIFIED": "20240920T051459Z",
          "SEQUENCE": "0",
          "STATUS": "CONFIRMED",
          "SUMMARY": "Hiunchuli & Saipal House Picnic",
          "TRANSP": "TRANSPARENT"
        },
        {
          "DTSTART;VALUE=DATE": "20250201",
          "DTEND;VALUE=DATE": "20250202",
          "DTSTAMP": "20250215T075322Z",
          "UID": "2tehvvobl3e0rg2d9rsb5v3o4a@google.com",
          "CREATED": "20240920T051517Z",
          "LAST-MODIFIED": "20240920T051517Z",
          "SEQUENCE": "0",
          "STATUS": "CONFIRMED",
          "SUMMARY": "Nilgiri and Pumori House Day Trek ",
          "TRANSP": "TRANSPARENT"
        },
        {
          "DTSTART;VALUE=DATE": "20250201",
          "DTEND;VALUE=DATE": "20250202",
          "DTSTAMP": "20250215T075322Z",
          "UID": "3krn7cmjbhick18pmle11svu71@google.com",
          "CREATED": "20240920T051528Z",
          "LAST-MODIFIED": "20240920T051528Z",
          "SEQUENCE": "0",
          "STATUS": "CONFIRMED",
          "SUMMARY": "ICAFT Begins",
          "TRANSP": "TRANSPARENT"
        },
        {
          "DTSTART;VALUE=DATE": "20250202",
          "DTEND;VALUE=DATE": "20250203",
          "DTSTAMP": "20250215T075322Z",
          "UID": "57rsr92pgqah6n7iovh9d0bkp4@google.com",
          "CREATED": "20241225T081217Z",
          "LAST-MODIFIED": "20241225T081217Z",
          "SEQUENCE": "0",
          "STATUS": "CONFIRMED",
          "SUMMARY": "Summer Time-table starts",
          "TRANSP": "TRANSPARENT"
        },
        {
          "DTSTART;VALUE=DATE": "20250202",
          "DTEND;VALUE=DATE": "20250203",
          "DTSTAMP": "20250215T075322Z",
          "UID": "076epksn518ihcdhgb65ckbfu6@google.com",
          "CREATED": "20241225T081258Z",
          "LAST-MODIFIED": "20241225T081258Z",
          "SEQUENCE": "0",
          "STATUS": "CONFIRMED",
          "SUMMARY": "Project Presentation for Post SEE begins (Physics Dept.)",
          "TRANSP": "TRANSPARENT"
        },
        {
          "DTSTART;VALUE=DATE": "20250202",
          "DTEND;VALUE=DATE": "20250203",
          "DTSTAMP": "20250215T075322Z",
          "UID": "3vuacfn55juf9maeahfo3a2dd3@google.com",
          "CREATED": "20241225T081335Z",
          "LAST-MODIFIED": "20241225T081335Z",
          "SEQUENCE": "0",
          "STATUS": "CONFIRMED",
          "SUMMARY": "C.R. Shakya Week Begins",
          "TRANSP": "TRANSPARENT"
        },
        {
          "DTSTART;VALUE=DATE": "20250203",
          "DTEND;VALUE=DATE": "20250204",
          "DTSTAMP": "20250215T075322Z",
          "UID": "1u40qge1heipspb4ppjnkk4vk6@google.com",
          "CREATED": "20241225T081408Z",
          "LAST-MODIFIED": "20241225T081408Z",
          "SEQUENCE": "0",
          "STATUS": "CONFIRMED",
          "SUMMARY": "Shri Panchami",
          "TRANSP": "TRANSPARENT"
        },
        {
          "DTSTART;VALUE=DATE": "20250204",
          "DTEND;VALUE=DATE": "20250205",
          "DTSTAMP": "20250215T075322Z",
          "UID": "0lctug2n25ig53h367hgpq97nf@google.com",
          "CREATED": "20241225T081421Z",
          "LAST-MODIFIED": "20241225T081421Z",
          "SEQUENCE": "0",
          "STATUS": "CONFIRMED",
          "SUMMARY": "Grade Review Meeting",
          "TRANSP": "TRANSPARENT"
        },
        {
          "DTSTART": "20250206T025000Z",
          "DTEND": "20250206T035000Z",
          "DTSTAMP": "20250215T075322Z",
          "UID": "7fgs42b9aua1ssk5tbvnr613ee@google.com",
          "CREATED": "20241225T081510Z",
          "LAST-MODIFIED": "20241225T081510Z",
          "SEQUENCE": "0",
          "STATUS": "CONFIRMED",
          "SUMMARY": "School Assembly (BL)",
          "TRANSP": "OPAQUE"
        },
        {
          "DTSTART;VALUE=DATE": "20250206",
          "DTEND;VALUE=DATE": "20250207",
          "DTSTAMP": "20250215T075322Z",
          "UID": "5dbcvhvqjmgevf5a1910c1glbn@google.com",
          "CREATED": "20241225T081545Z",
          "LAST-MODIFIED": "20241225T081545Z",
          "SEQUENCE": "0",
          "STATUS": "CONFIRMED",
          "SUMMARY": "Project Presentation for Post SEE Ends Physics Dept.)",
          "TRANSP": "TRANSPARENT"
        },
        {
          "DTSTART;VALUE=DATE": "20250206",
          "DTEND;VALUE=DATE": "20250207",
          "DTSTAMP": "20250215T075322Z",
          "UID": "742tp4bafddvtd4ts1qi59a9te@google.com",
          "CREATED": "20241225T081621Z",
          "LAST-MODIFIED": "20241225T081621Z",
          "SEQUENCE": "0",
          "STATUS": "CONFIRMED",
          "SUMMARY": "C.R. Shakya Week Ends",
          "TRANSP": "TRANSPARENT"
        },
        {
          "DTSTART;VALUE=DATE": "20250207",
          "DTEND;VALUE=DATE": "20250208",
          "DTSTAMP": "20250215T075322Z",
          "UID": "6k47r91n1pp17qsmjtf9c2gphc@google.com",
          "CREATED": "20241225T081643Z",
          "LAST-MODIFIED": "20241225T081643Z",
          "SEQUENCE": "0",
          "STATUS": "CONFIRMED",
          "SUMMARY": "Class 10 Trial Examination Begins",
          "TRANSP": "TRANSPARENT"
        },
        {
          "DTSTART": "20250207T134500Z",
          "DTEND": "20250207T144500Z",
          "DTSTAMP": "20250215T075322Z",
          "UID": "4692fdpr3n0ulm3qtkfmhhmbq2@google.com",
          "CREATED": "20241225T081732Z",
          "LAST-MODIFIED": "20241225T081732Z",
          "SEQUENCE": "0",
          "STATUS": "CONFIRMED",
          "SUMMARY": "PH Cultural Night",
          "TRANSP": "OPAQUE"
        },
        {
          "DTSTART;VALUE=DATE": "20250208",
          "DTEND;VALUE=DATE": "20250209",
          "DTSTAMP": "20250215T075322Z",
          "UID": "347ri0h3q8od0tmf0i4pmefs8q@google.com",
          "CREATED": "20241225T081809Z",
          "LAST-MODIFIED": "20241225T081809Z",
          "SEQUENCE": "0",
          "STATUS": "CONFIRMED",
          "SUMMARY": "Dhaulagiri and Makalu House Picnic",
          "TRANSP": "TRANSPARENT"
        },
        {
          "DTSTART;VALUE=DATE": "20250208",
          "DTEND;VALUE=DATE": "20250209",
          "DTSTAMP": "20250215T075322Z",
          "UID": "5adjf0fe47fm604t123kban535@google.com",
          "CREATED": "20241225T081843Z",
          "LAST-MODIFIED": "20241225T081843Z",
          "SEQUENCE": "0",
          "STATUS": "CONFIRMED",
          "SUMMARY": "ICAFT Ends (Closing Ceremony)",
          "TRANSP": "TRANSPARENT"
        },
        {
          "DTSTART;VALUE=DATE": "20250209",
          "DTEND;VALUE=DATE": "20250210",
          "DTSTAMP": "20250215T075322Z",
          "UID": "3rnhicprtu3j1m4534pmhi076m@google.com",
          "CREATED": "20241225T081949Z",
          "LAST-MODIFIED": "20241225T081949Z",
          "SEQUENCE": "0",
          "STATUS": "CONFIRMED",
          "SUMMARY": "Panel Discussion (Biology Department)",
          "TRANSP": "TRANSPARENT"
        },
        {
          "DTSTART;VALUE=DATE": "20250210",
          "DTEND;VALUE=DATE": "20250211",
          "DTSTAMP": "20250215T075322Z",
          "UID": "72vs1caggk3mm8sjjmo5uh4s2r@google.com",
          "CREATED": "20241225T082023Z",
          "LAST-MODIFIED": "20241225T082023Z",
          "SEQUENCE": "0",
          "STATUS": "CONFIRMED",
          "SUMMARY": "School Assembly (SL) 8:10 AM",
          "TRANSP": "TRANSPARENT"
        },
        {
          "DTSTART;VALUE=DATE": "20250211",
          "DTEND;VALUE=DATE": "20250212",
          "DTSTAMP": "20250215T075322Z",
          "UID": "5q5mc4vcgd408m1jdmnn5p3lrc@google.com",
          "CREATED": "20241225T082103Z",
          "LAST-MODIFIED": "20241225T082103Z",
          "SEQUENCE": "0",
          "STATUS": "CONFIRMED",
          "SUMMARY": "Three Day Workshop Begins (Scout club) 4\\;30 PM",
          "TRANSP": "TRANSPARENT"
        },
        {
          "DTSTART;VALUE=DATE": "20250213",
          "DTEND;VALUE=DATE": "20250214",
          "DTSTAMP": "20250215T075322Z",
          "UID": "0dpcp1cab8dcs1q16dv3m8s8mm@google.com",
          "CREATED": "20241225T082142Z",
          "LAST-MODIFIED": "20241225T082142Z",
          "SEQUENCE": "0",
          "STATUS": "CONFIRMED",
          "SUMMARY": "Three Day Workshop Ends ",
          "TRANSP": "TRANSPARENT"
        },
        {
          "DTSTART;VALUE=DATE": "20250213",
          "DTEND;VALUE=DATE": "20250214",
          "DTSTAMP": "20250215T075322Z",
          "UID": "06v33m5c262l5ss7clric5k5n2@google.com",
          "CREATED": "20241225T082219Z",
          "LAST-MODIFIED": "20241225T082219Z",
          "SEQUENCE": "0",
          "STATUS": "CONFIRMED",
          "SUMMARY": "Exploration in Science 2081 (Int. Science Dept.)",
          "TRANSP": "TRANSPARENT"
        },
        {
          "DTSTART;VALUE=DATE": "20250214",
          "DTEND;VALUE=DATE": "20250215",
          "DTSTAMP": "20250215T075322Z",
          "UID": "46mlbf568blfi3i280sgj60a7d@google.com",
          "CREATED": "20241225T082239Z",
          "LAST-MODIFIED": "20241225T082239Z",
          "SEQUENCE": "0",
          "STATUS": "CONFIRMED",
          "SUMMARY": "Class 10 Trial Examination Ends",
          "TRANSP": "TRANSPARENT"
        },
        {
          "DTSTART;VALUE=DATE": "20250215",
          "DTEND;VALUE=DATE": "20250216",
          "DTSTAMP": "20250215T075322Z",
          "UID": "5gp24dvndnvademolk5crj2cof@google.com",
          "CREATED": "20241225T082330Z",
          "LAST-MODIFIED": "20241225T082330Z",
          "SEQUENCE": "0",
          "STATUS": "CONFIRMED",
          "SUMMARY": "Idea Pitch (Photography & FYE club) ",
          "TRANSP": "TRANSPARENT"
        },
        {
          "DTSTART;VALUE=DATE": "20250215",
          "DTEND;VALUE=DATE": "20250216",
          "DTSTAMP": "20250215T075322Z",
          "UID": "7q0m9h0etjt25irpt83km0o7gf@google.com",
          "CREATED": "20241225T082351Z",
          "LAST-MODIFIED": "20241225T082351Z",
          "SEQUENCE": "0",
          "STATUS": "CONFIRMED",
          "SUMMARY": "Blood Donation Program (YRC)",
          "TRANSP": "TRANSPARENT"
        },
        {
          "DTSTART;VALUE=DATE": "20250218",
          "DTEND;VALUE=DATE": "20250219",
          "DTSTAMP": "20250215T075322Z",
          "UID": "0rmk6ajoeoemudkpnqdilhosli@google.com",
          "CREATED": "20241225T082411Z",
          "LAST-MODIFIED": "20241225T082411Z",
          "SEQUENCE": "0",
          "STATUS": "CONFIRMED",
          "SUMMARY": "School Day",
          "TRANSP": "TRANSPARENT"
        },
        {
          "DTSTART;VALUE=DATE": "20250218",
          "DTEND;VALUE=DATE": "20250219",
          "DTSTAMP": "20250215T075322Z",
          "UID": "1t1opq2667g19kiudc0dtt0v01@google.com",
          "CREATED": "20241225T082432Z",
          "LAST-MODIFIED": "20241225T082432Z",
          "SEQUENCE": "0",
          "STATUS": "CONFIRMED",
          "SUMMARY": "Students may go home after program",
          "TRANSP": "TRANSPARENT"
        },
        {
          "DTSTART;VALUE=DATE": "20250219",
          "DTEND;VALUE=DATE": "20250220",
          "DTSTAMP": "20250215T075322Z",
          "UID": "5reu6h6rjptlo745u8tjbg8f18@google.com",
          "CREATED": "20241225T082448Z",
          "LAST-MODIFIED": "20241225T082448Z",
          "SEQUENCE": "0",
          "STATUS": "CONFIRMED",
          "SUMMARY": "National Democracy Day",
          "TRANSP": "TRANSPARENT"
        },
        {
          "DTSTART;VALUE=DATE": "20250219",
          "DTEND;VALUE=DATE": "20250220",
          "DTSTAMP": "20250215T075322Z",
          "UID": "0cagn22h8dv674roncd4u8f8i8@google.com",
          "CREATED": "20241225T082510Z",
          "LAST-MODIFIED": "20241225T082510Z",
          "SEQUENCE": "0",
          "STATUS": "CONFIRMED",
          "SUMMARY": "Class 9 Social Studies Visit Begins",
          "TRANSP": "TRANSPARENT"
        },
        {
          "DTSTART": "20250220T123000Z",
          "DTEND": "20250220T133000Z",
          "DTSTAMP": "20250215T075322Z",
          "UID": "4gnosbafrgcavhd3csvbtra8rt@google.com",
          "CREATED": "20241225T082558Z",
          "LAST-MODIFIED": "20241225T082558Z",
          "SEQUENCE": "0",
          "STATUS": "CONFIRMED",
          "SUMMARY": "Students must return by:",
          "TRANSP": "OPAQUE"
        },
        {
          "DTSTART;VALUE=DATE": "20250221",
          "DTEND;VALUE=DATE": "20250222",
          "DTSTAMP": "20250215T075322Z",
          "UID": "5f95o2jobki0kvcpb9tq3vvtup@google.com",
          "CREATED": "20241225T082630Z",
          "LAST-MODIFIED": "20241225T082630Z",
          "SEQUENCE": "0",
          "STATUS": "CONFIRMED",
          "SUMMARY": "College Fair",
          "TRANSP": "TRANSPARENT"
        },
        {
          "DTSTART;VALUE=DATE": "20250223",
          "DTEND;VALUE=DATE": "20250224",
          "DTSTAMP": "20250215T075322Z",
          "UID": "533oilokp0gnhau6vqkh1lacn2@google.com",
          "CREATED": "20241225T082707Z",
          "LAST-MODIFIED": "20241225T082707Z",
          "SEQUENCE": "0",
          "STATUS": "CONFIRMED",
          "SUMMARY": "Class 9 Social Studies visit Ends",
          "TRANSP": "TRANSPARENT"
        },
        {
          "DTSTART": "20250224T024000Z",
          "DTEND": "20250224T034000Z",
          "DTSTAMP": "20250215T075322Z",
          "UID": "1potb80qni47kmv05mepfscsar@google.com",
          "CREATED": "20241225T082741Z",
          "LAST-MODIFIED": "20241225T082741Z",
          "SEQUENCE": "0",
          "STATUS": "CONFIRMED",
          "SUMMARY": "School Assembly (BL)",
          "TRANSP": "OPAQUE"
        },
        {
          "DTSTART;VALUE=DATE": "20250224",
          "DTEND;VALUE=DATE": "20250225",
          "DTSTAMP": "20250215T075322Z",
          "UID": "3n42837b5350at0cl3jbot0u9h@google.com",
          "CREATED": "20241225T082800Z",
          "LAST-MODIFIED": "20241225T082800Z",
          "SEQUENCE": "0",
          "STATUS": "CONFIRMED",
          "SUMMARY": "Nilgiri House Presentation",
          "TRANSP": "TRANSPARENT"
        },
        {
          "DTSTART;VALUE=DATE": "20250224",
          "DTEND;VALUE=DATE": "20250225",
          "DTSTAMP": "20250215T075322Z",
          "UID": "138jbdke2qccbo0ri37lg8gnf0@google.com",
          "CREATED": "20241225T082831Z",
          "LAST-MODIFIED": "20241225T082831Z",
          "SEQUENCE": "0",
          "STATUS": "CONFIRMED",
          "SUMMARY": "Integrated science Visit for Grade 8",
          "TRANSP": "TRANSPARENT"
        },
        {
          "DTSTART;VALUE=DATE": "20250226",
          "DTEND;VALUE=DATE": "20250227",
          "DTSTAMP": "20250215T075322Z",
          "UID": "5quqf67nh99hpn28dvp5376nlm@google.com",
          "CREATED": "20241225T082859Z",
          "LAST-MODIFIED": "20241225T082859Z",
          "SEQUENCE": "0",
          "STATUS": "CONFIRMED",
          "SUMMARY": "Mahashivaratri - a holiday",
          "TRANSP": "TRANSPARENT"
        },
        {
          "DTSTART;VALUE=DATE": "20250227",
          "DTEND;VALUE=DATE": "20250228",
          "DTSTAMP": "20250215T075322Z",
          "UID": "4ektchnobfudqu5vnb2s1unnpr@google.com",
          "CREATED": "20241225T082931Z",
          "LAST-MODIFIED": "20241225T082931Z",
          "SEQUENCE": "0",
          "STATUS": "CONFIRMED",
          "SUMMARY": "Integrated Science Visit for grade 8",
          "TRANSP": "TRANSPARENT"
        },
        {
          "DTSTART;VALUE=DATE": "20250228",
          "DTEND;VALUE=DATE": "20250301",
          "DTSTAMP": "20250215T075322Z",
          "UID": "5dk3b035d3pkucq4q71qae6kn6@google.com",
          "CREATED": "20241225T082953Z",
          "LAST-MODIFIED": "20241225T082953Z",
          "SEQUENCE": "0",
          "STATUS": "CONFIRMED",
          "SUMMARY": "Junior School Play (BL)",
          "TRANSP": "TRANSPARENT"
        },
        {
          "DTSTART;VALUE=DATE": "20250228",
          "DTEND;VALUE=DATE": "20250301",
          "DTSTAMP": "20250215T075322Z",
          "UID": "31alr5o0l18evb9o0dqbrjvcdd@google.com",
          "CREATED": "20241225T083030Z",
          "LAST-MODIFIED": "20241225T083030Z",
          "SEQUENCE": "0",
          "STATUS": "CONFIRMED",
          "SUMMARY": "Course Completion of A1 & A2",
          "TRANSP": "TRANSPARENT"
        },
        {
          "DTSTART;VALUE=DATE": "20250228",
          "DTEND;VALUE=DATE": "20250301",
          "DTSTAMP": "20250215T075322Z",
          "UID": "4nq49v11k2d3hgsgev2imam4ro@google.com",
          "CREATED": "20241225T083059Z",
          "LAST-MODIFIED": "20241225T083059Z",
          "SEQUENCE": "0",
          "STATUS": "CONFIRMED",
          "SUMMARY": "Gyalpo Lhosar",
          "TRANSP": "TRANSPARENT"
        },
        {
          "DTSTART": "20250301T073000Z",
          "DTEND": "20250301T083000Z",
          "DTSTAMP": "20250215T075322Z",
          "UID": "3vok02sd7d7i040nl3bm4etmo3@google.com",
          "CREATED": "20241225T083131Z",
          "LAST-MODIFIED": "20241225T083131Z",
          "SEQUENCE": "0",
          "STATUS": "CONFIRMED",
          "SUMMARY": "Junior School Play for Parents (English)",
          "TRANSP": "OPAQUE"
        },
        {
          "DTSTART;VALUE=DATE": "20250302",
          "DTEND;VALUE=DATE": "20250303",
          "DTSTAMP": "20250215T075322Z",
          "UID": "78j8chrjukafuaouivbddl8au1@google.com",
          "CREATED": "20241225T083209Z",
          "LAST-MODIFIED": "20241225T083209Z",
          "SEQUENCE": "0",
          "STATUS": "CONFIRMED",
          "SUMMARY": "Class 10 Mock SEE Examination Begins ",
          "TRANSP": "TRANSPARENT"
        },
        {
          "DTSTART;VALUE=DATE": "20250307",
          "DTEND;VALUE=DATE": "20250308",
          "DTSTAMP": "20250215T075322Z",
          "UID": "5f3tbjmccdapa1inonc5vofmnh@google.com",
          "CREATED": "20241225T083241Z",
          "LAST-MODIFIED": "20241225T083241Z",
          "SEQUENCE": "0",
          "STATUS": "CONFIRMED",
          "SUMMARY": "Course Completion of Class 12",
          "TRANSP": "TRANSPARENT"
        },
        {
          "DTSTART;VALUE=DATE": "20250308",
          "DTEND;VALUE=DATE": "20250309",
          "DTSTAMP": "20250215T075322Z",
          "UID": "25hd6d844lj26f4jk10jqp1rvi@google.com",
          "CREATED": "20241225T083312Z",
          "LAST-MODIFIED": "20241225T083312Z",
          "SEQUENCE": "0",
          "STATUS": "CONFIRMED",
          "SUMMARY": "International Women`s Day",
          "TRANSP": "TRANSPARENT"
        },
        {
          "DTSTART;VALUE=DATE": "20250308",
          "DTEND;VALUE=DATE": "20250309",
          "DTSTAMP": "20250215T075322Z",
          "UID": "1lrg9h1rm0chid0fba2hted4ve@google.com",
          "CREATED": "20241225T083354Z",
          "LAST-MODIFIED": "20241225T083354Z",
          "SEQUENCE": "0",
          "STATUS": "CONFIRMED",
          "SUMMARY": "Dhaulagiri House and Makalu House Day Trek",
          "TRANSP": "TRANSPARENT"
        },
        {
          "DTSTART;VALUE=DATE": "20250309",
          "DTEND;VALUE=DATE": "20250310",
          "DTSTAMP": "20250215T075322Z",
          "UID": "3iiquckvdckobb0hj1a9t73lsr@google.com",
          "CREATED": "20241225T083430Z",
          "LAST-MODIFIED": "20241225T083430Z",
          "SEQUENCE": "0",
          "STATUS": "CONFIRMED",
          "SUMMARY": "Class 10 Mock SEE Examination Ends ",
          "TRANSP": "TRANSPARENT"
        },
        {
          "DTSTART;VALUE=DATE": "20250310",
          "DTEND;VALUE=DATE": "20250311",
          "DTSTAMP": "20250215T075322Z",
          "UID": "407eu20fkadkfsui54tj48q7dc@google.com",
          "CREATED": "20241225T083445Z",
          "LAST-MODIFIED": "20241225T083500Z",
          "SEQUENCE": "0",
          "STATUS": "CONFIRMED",
          "SUMMARY": "School Assembly (SL) 8:10 AM",
          "TRANSP": "TRANSPARENT"
        },
        {
          "DTSTART;VALUE=DATE": "20250312",
          "DTEND;VALUE=DATE": "20250313",
          "DTSTAMP": "20250215T075322Z",
          "UID": "096jh4qj2sut3ucf7clr9vqp3g@google.com",
          "CREATED": "20241225T083558Z",
          "LAST-MODIFIED": "20241225T083558Z",
          "SEQUENCE": "0",
          "STATUS": "CONFIRMED",
          "SUMMARY": "A1/A2 Trial Examination Begins",
          "TRANSP": "TRANSPARENT"
        },
        {
          "DTSTART;VALUE=DATE": "20250313",
          "DTEND;VALUE=DATE": "20250314",
          "DTSTAMP": "20250215T075322Z",
          "UID": "5feulgatlts1petnmet2s97iv0@google.com",
          "CREATED": "20241225T083615Z",
          "LAST-MODIFIED": "20241225T083615Z",
          "SEQUENCE": "0",
          "STATUS": "CONFIRMED",
          "SUMMARY": "Holi Purnima - a holiday",
          "TRANSP": "TRANSPARENT"
        },
        {
          "DTSTART": "20250314T113000Z",
          "DTEND": "20250314T153000Z",
          "DTSTAMP": "20250215T075322Z",
          "UID": "1ci38d0gtvfdknsvskl3cfjc9m@google.com",
          "CREATED": "20241225T083635Z",
          "LAST-MODIFIED": "20241225T083635Z",
          "SEQUENCE": "0",
          "STATUS": "CONFIRMED",
          "SUMMARY": "Course Completion for Grades",
          "TRANSP": "OPAQUE"
        },
        {
          "DTSTART": "20250321T113000Z",
          "DTEND": "20250321T133000Z",
          "DTSTAMP": "20250215T075322Z",
          "UID": "4lkur9dooat8jlghfvtg264ijb@google.com",
          "CREATED": "20241225T083705Z",
          "LAST-MODIFIED": "20241225T083705Z",
          "SEQUENCE": "0",
          "STATUS": "CONFIRMED",
          "SUMMARY": "Second Semester Exam (",
          "TRANSP": "OPAQUE"
        },
        {
          "DTSTART;VALUE=DATE": "20250321",
          "DTEND;VALUE=DATE": "20250322",
          "DTSTAMP": "20250215T075322Z",
          "UID": "18tpd1lh742h1a991k6dpo3pkj@google.com",
          "CREATED": "20241225T083736Z",
          "LAST-MODIFIED": "20241225T083736Z",
          "SEQUENCE": "0",
          "STATUS": "CONFIRMED",
          "SUMMARY": "Final Exam (9) Trial Exam (Class 12) Begin",
          "TRANSP": "TRANSPARENT"
        },
        {
          "DTSTART;VALUE=DATE": "20250321",
          "DTEND;VALUE=DATE": "20250322",
          "DTSTAMP": "20250215T075322Z",
          "UID": "033rdr0drpvn5v5emsicrcrusq@google.com",
          "CREATED": "20241225T083755Z",
          "LAST-MODIFIED": "20241225T083755Z",
          "SEQUENCE": "0",
          "STATUS": "CONFIRMED",
          "SUMMARY": "Course Completion of Grade 11",
          "TRANSP": "TRANSPARENT"
        },
        {
          "DTSTART;VALUE=DATE": "20250322",
          "DTEND;VALUE=DATE": "20250323",
          "DTSTAMP": "20250215T075322Z",
          "UID": "0ej8dsmppqdv6kfrno08tl5100@google.com",
          "CREATED": "20241225T083813Z",
          "LAST-MODIFIED": "20241225T083813Z",
          "SEQUENCE": "0",
          "STATUS": "CONFIRMED",
          "SUMMARY": "Teaching Staff Picnic",
          "TRANSP": "TRANSPARENT"
        },
        {
          "DTSTART;VALUE=DATE": "20250328",
          "DTEND;VALUE=DATE": "20250329",
          "DTSTAMP": "20250215T075322Z",
          "UID": "73c4pceus3phlg5qn8ntdgauue@google.com",
          "CREATED": "20241225T083831Z",
          "LAST-MODIFIED": "20241225T083831Z",
          "SEQUENCE": "0",
          "STATUS": "CONFIRMED",
          "SUMMARY": "Examination End",
          "TRANSP": "TRANSPARENT"
        },
        {
          "DTSTART": "20250301T090000Z",
          "DTEND": "20250301T100000Z",
          "DTSTAMP": "20250215T075322Z",
          "UID": "3rvdj30ontm01c3odd1r49cgsf@google.com",
          "CREATED": "20241225T083854Z",
          "LAST-MODIFIED": "20241225T083854Z",
          "SEQUENCE": "0",
          "STATUS": "CONFIRMED",
          "SUMMARY": "Class 11 Trial Examination Begins",
          "TRANSP": "OPAQUE"
        },
        {
          "DTSTART;VALUE=DATE": "20250329",
          "DTEND;VALUE=DATE": "20250330",
          "DTSTAMP": "20250215T075322Z",
          "UID": "72o0iog1d1cbh8vmo2vr6v9rhi@google.com",
          "CREATED": "20241225T083905Z",
          "LAST-MODIFIED": "20241225T083905Z",
          "SEQUENCE": "0",
          "STATUS": "CONFIRMED",
          "SUMMARY": "Ghodejatra",
          "TRANSP": "TRANSPARENT"
        },
        {
          "DTSTART;VALUE=DATE": "20250404",
          "DTEND;VALUE=DATE": "20250405",
          "DTSTAMP": "20250215T075322Z",
          "UID": "45fco8fsprjoe1on5n8lnh262m@google.com",
          "CREATED": "20241225T083934Z",
          "LAST-MODIFIED": "20241225T083934Z",
          "SEQUENCE": "0",
          "STATUS": "CONFIRMED",
          "SUMMARY": "Class 11 Trial Exam ends",
          "TRANSP": "TRANSPARENT"
        },
        {
          "DTSTART;VALUE=DATE": "20250404",
          "DTEND;VALUE=DATE": "20250405",
          "DTSTAMP": "20250215T075322Z",
          "UID": "1eqkji95j2dbu23ulrmv1688ts@google.com",
          "CREATED": "20241225T084000Z",
          "LAST-MODIFIED": "20241225T084000Z",
          "SEQUENCE": "0",
          "STATUS": "CONFIRMED",
          "SUMMARY": "Report Card Distribution ",
          "TRANSP": "TRANSPARENT"
        },
        {
          "DTSTART;VALUE=DATE": "20250404",
          "DTEND;VALUE=DATE": "20250405",
          "DTSTAMP": "20250215T075322Z",
          "UID": "42ismrkppk9qcjj5d5ohge8bnb@google.com",
          "CREATED": "20241225T084100Z",
          "LAST-MODIFIED": "20241225T084100Z",
          "SEQUENCE": "0",
          "STATUS": "CONFIRMED",
          "SUMMARY": "Academic Year 2082 begins on May 2\\, 2025",
          "TRANSP": "TRANSPARENT"
        },
        {
          "DTSTART;VALUE=DATE": "20250404",
          "DTEND;VALUE=DATE": "20250405",
          "DTSTAMP": "20250215T075322Z",
          "UID": "0br2qdu5ghb50f7n19rv77rdii@google.com",
          "CREATED": "20241225T084145Z",
          "LAST-MODIFIED": "20241225T084145Z",
          "SEQUENCE": "0",
          "STATUS": "CONFIRMED",
          "SUMMARY": "Baishak 18\\, 2082) Thursday ",
          "TRANSP": "TRANSPARENT"
        },
        {
          "DTSTART": "20250401T090000Z",
          "DTEND": "20250401T100000Z",
          "DTSTAMP": "20250215T075322Z",
          "UID": "5l6md8irrrr0e7fojnjd3bagbp@google.com",
          "CREATED": "20241225T084229Z",
          "LAST-MODIFIED": "20241225T084229Z",
          "SEQUENCE": "0",
          "STATUS": "CONFIRMED",
          "SUMMARY": "Class 5 Fee-payers Entrance Test 9:00 AM",
          "TRANSP": "OPAQUE"
        },
        {
          "DTSTART;VALUE=DATE": "20250405",
          "DTEND;VALUE=DATE": "20250406",
          "DTSTAMP": "20250215T075322Z",
          "UID": "1q4k6luv1bn2eqcuopo3aqh0ku@google.com",
          "CREATED": "20241225T084319Z",
          "LAST-MODIFIED": "20241225T084319Z",
          "SEQUENCE": "0",
          "STATUS": "CONFIRMED",
          "SUMMARY": "Class 5 Fee-payers Entrance Test",
          "TRANSP": "TRANSPARENT"
        }
      ]
    }
  ]
}